{
  "kind": "collectionType",
  "collectionName": "collections",
  "info": {
    "singularName": "collection",
    "pluralName": "collections",
    "displayName": "Collection"
  },
  "options": {
    "draftAndPublish": true
  },
  "pluginOptions": {},
  "attributes": {
    "images": {
      "allowedTypes": [
        "images",
        "files",
        "videos",
        "audios"
      ],
      "type": "media",
      "multiple": true
    },
    "title": {
      "type": "string"
    },
    "type": {
      "type": "enumeration",
      "enum": [
        "film",
        "digital"
      ]
    },
    "description": {
      "type": "text"
    }
  }
}
